{"duration": 4.013561010360718, "input_args": {"transformer": "Pipeline(steps=[('mc', MisCare(missing_threshold=0.05)), ('cc', ConstantCare()),\n                ('ur', URareCare(threshold=0.025)), ('cc2', ConstantCare()),\n                ('one_hot', CustomOneHotEncoder()),\n                ('feature_selection',\n                 FeatureSelection(alpha=0.1, model_type='reg')),\n                ('collinear_care',\n                 CollinearCare(dist_method='correlation', threshold=0.01))])", "X": "         p1   p2   p3   p4   p5   p6   p7  ... p343 p344 p345 p346 p347 p348 p349\nBovine    M    N    G    T    E    G    P  ...  NaN    S    Q    V    A    P    A\nS1        M    N    G    T    E    G    P  ...    A    S    S    V    S    P    A\nS2      NaN  NaN  NaN    T    E    G    P  ...    A    S    S    V    S    P    A\nS3      NaN  NaN  NaN    T    E    G    P  ...    A    S    S    V    S    P    A\nS4      NaN  NaN  NaN    T    E    G    P  ...    A    S    S    V    S    P    A\n...     ...  ...  ...  ...  ...  ...  ...  ...  ...  ...  ...  ...  ...  ...  ...\nMNM872  NaN  NaN  NaN  NaN  NaN  NaN  NaN  ...  NaN  NaN  NaN  NaN  NaN  NaN  NaN\nMNM873  NaN  NaN  NaN  NaN  NaN  NaN  NaN  ...  NaN  NaN  NaN  NaN  NaN  NaN  NaN\nMNM874  NaN  NaN  NaN  NaN  NaN  NaN  NaN  ...  NaN  NaN  NaN  NaN    S    S  NaN\nMNM875  NaN  NaN  NaN  NaN  NaN  NaN  NaN  ...  NaN  NaN  NaN  NaN  NaN  NaN  NaN\nMNM876    M    A  NaN  NaN    P    G    M  ...    C    E    K  NaN    S    A  NaN\n\n[789 rows x 349 columns]", "y": "array([500.  , 502.  , 502.  , 481.  , 494.  , 494.  , 491.  , 486.  ,\n       490.  , 490.  , 499.  , 493.  , 498.  , 495.  , 499.  , 492.  ,\n       501.  , 488.  , 487.  , 498.  , 502.  , 488.  , 501.  , 504.  ,\n       496.  , 500.  , 498.  , 505.  , 500.  , 490.  , 498.  , 502.  ,\n       488.  , 501.  , 488.  , 491.  , 503.  , 500.  , 491.  , 497.  ,\n       494.  , 492.  , 489.  , 501.  , 501.  , 501.  , 501.  , 482.  ,\n       502.  , 501.  , 502.  , 496.  , 485.  , 486.  , 486.  , 485.  ,\n       496.  , 483.  , 526.  , 489.  , 492.  , 486.  , 491.  , 479.  ,\n       504.  , 489.  , 524.  , 467.  , 452.  , 496.  , 467.  , 476.  ,\n       488.  , 505.  , 501.  , 560.9 , 463.  , 355.  , 425.  , 356.  ,\n       358.  , 360.  , 393.  , 359.  , 417.  , 360.  , 359.  , 358.  ,\n       420.  , 419.  , 420.  , 489.  , 482.  , 501.  , 496.5 , 502.  ,\n       571.  , 540.  , 492.  , 505.  , 502.  , 502.  , 500.  , 506.  ,\n       502.  , 502.  , 503.  , 511.  , 506.  , 503.  , 511.  , 437.  ,\n       441.  , 455.  , 558.  , 560.  , 571.  , 532.  , 563.  , 553.  ,\n       509.  , 508.  , 509.  , 553.  , 545.  , 531.  , 516.  , 532.  ,\n       500.  , 569.  , 352.  , 578.  , 571.  , 562.  , 516.  , 519.  ,\n       516.  , 476.  , 438.  , 408.  , 503.  , 358.  , 439.  , 508.  ,\n       505.  , 498.  , 483.  , 480.  , 450.  , 420.  , 500.  , 499.  ,\n       404.  , 450.  , 486.  , 479.  , 539.  , 502.  , 525.  , 496.  ,\n       435.  , 439.  , 516.  , 492.  , 448.  , 494.  , 447.  , 517.  ,\n       469.  , 491.  , 460.  , 519.  , 491.  , 462.  , 517.  , 493.  ,\n       485.  , 416.  , 452.  , 466.  , 439.  , 405.  , 448.  , 397.  ,\n       416.  , 505.  , 528.  , 519.  , 423.  , 368.  , 507.  , 508.  ,\n       488.  , 491.  , 491.  , 489.  , 505.  , 488.  , 489.  , 474.  ,\n       524.  , 488.  , 499.  , 497.  , 500.  , 478.  , 361.  , 360.  ,\n       359.  , 360.  , 360.  , 393.  , 359.  , 393.  , 552.  , 363.  ,\n       431.  , 356.  , 442.  , 584.  , 509.  , 572.  , 563.  , 563.  ,\n       561.  , 558.  , 558.  , 536.  , 561.  , 564.  , 532.  , 553.  ,\n       532.  , 359.  , 403.  , 539.  , 611.  , 542.  , 557.  , 577.  ,\n       532.  , 532.  , 537.  , 518.  , 482.  , 431.  , 485.  , 482.  ,\n       494.  , 490.  , 551.  , 532.  , 545.  , 430.  , 430.  , 340.  ,\n       346.  , 350.  , 513.  , 364.  , 359.  , 360.  , 371.  , 355.  ,\n       423.  , 360.  , 425.  , 456.  , 472.  , 517.  , 528.  , 560.  ,\n       356.  , 561.  , 562.  , 502.  , 488.  , 550.  , 497.  , 361.  ,\n       440.  , 363.  , 533.  , 535.  , 486.  , 500.  , 478.  , 500.  ,\n       514.  , 504.  , 449.  , 448.  , 460.  , 455.  , 457.  , 500.  ,\n       480.  , 486.8 , 481.  , 430.  , 499.  , 497.  , 499.  , 503.  ,\n       495.  , 497.  , 496.  , 496.  , 496.  , 487.  , 494.5 , 499.  ,\n       502.  , 501.  , 499.  , 499.  , 501.  , 501.  , 503.  , 501.  ,\n       501.  , 501.  , 499.  , 483.  , 529.  , 493.  , 499.  , 480.  ,\n       494.  , 475.  , 492.  , 523.  , 461.  , 497.  , 484.  , 566.  ,\n       567.  , 542.  , 565.  , 558.  , 547.  , 530.8 , 534.  , 561.  ,\n       540.  , 560.  , 537.  , 562.  , 563.  , 565.  , 562.  , 563.  ,\n       555.  , 551.  , 563.  , 526.  , 537.  , 535.  , 551.  , 553.  ,\n       535.  , 536.  , 540.  , 556.  , 563.  , 567.  , 554.  , 506.  ,\n       411.  , 510.  , 543.  , 556.  , 556.  , 545.  , 531.  , 558.  ,\n       561.  , 558.  , 517.  , 520.  , 563.  , 526.  , 528.  , 525.  ,\n       526.  , 525.  , 522.  , 482.  , 482.  , 484.  , 472.  , 504.  ,\n       506.  , 523.  , 519.  , 514.  , 527.  , 508.8 , 558.  , 355.  ,\n       362.  , 366.  , 512.  , 500.6 , 516.  , 523.  , 485.  , 475.  ,\n       506.  , 488.7 , 547.  , 492.  , 363.  , 352.  , 368.  , 366.  ,\n       369.  , 365.  , 380.  , 359.  , 370.  , 350.  , 508.  , 512.  ,\n       457.  , 393.  , 455.  , 455.  , 451.2 , 451.  , 450.  , 450.  ,\n       453.  , 453.  , 452.  , 457.  , 402.  , 404.  , 400.  , 465.  ,\n       459.  , 455.  , 456.  , 426.4 , 460.  , 452.  , 449.  , 370.  ,\n       508.  , 512.3 , 488.  , 504.  , 500.  , 460.  , 498.  , 528.  ,\n       475.  , 499.  , 500.  , 505.  , 502.  , 504.  , 500.  , 504.  ,\n       505.  , 505.  , 506.  , 504.  , 504.  , 504.  , 501.  , 466.  ,\n       482.  , 506.2 , 493.  , 484.  , 474.  , 504.  , 505.  , 500.  ,\n       501.  , 508.  , 523.  , 500.  , 505.  , 505.  , 512.  , 502.  ,\n       500.  , 502.  , 503.  , 502.  , 503.  , 515.7 , 504.8 , 496.  ,\n       517.8 , 498.  , 496.  , 496.  , 496.  , 500.  , 505.  , 506.  ,\n       505.  , 501.  , 502.  , 500.  , 496.  , 500.  , 498.  , 500.  ,\n       497.  , 497.  , 503.  , 505.  , 500.  , 500.  , 493.  , 487.  ,\n       497.  , 495.  , 487.  , 515.  , 509.  , 500.  , 503.  , 495.  ,\n       495.  , 492.  , 493.  , 491.  , 502.  , 506.  , 508.  , 507.  ,\n       510.  , 503.  , 498.  , 497.  , 492.  , 502.  , 503.  , 504.  ,\n       503.  , 503.  , 504.  , 503.  , 503.  , 500.  , 501.  , 502.  ,\n       500.  , 503.  , 503.  , 505.  , 505.  , 499.  , 495.  , 493.  ,\n       492.  , 491.7 , 439.  , 441.  , 441.  , 434.  , 437.  , 359.  ,\n       449.  , 498.  , 508.  , 509.  , 507.  , 505.  , 474.  , 415.  ,\n       426.  , 446.  , 460.  , 451.  , 446.  , 545.  , 443.  , 442.  ,\n       441.  , 415.  , 371.  , 435.  , 425.  , 405.  , 362.  , 424.  ,\n       362.  , 365.  , 360.  , 365.  , 363.  , 365.  , 365.  , 360.  ,\n       443.  , 431.  , 409.  , 366.  , 570.  , 534.  , 569.  , 556.  ,\n       557.  , 552.  , 561.  , 498.  , 562.  , 538.  , 557.  , 551.  ,\n       558.  , 555.  , 555.  , 360.  , 518.  , 515.  , 527.  , 516.  ,\n       524.  , 521.  , 506.  , 520.  , 516.  , 517.  , 505.  , 521.  ,\n       523.  , 531.  , 535.  , 490.  , 528.  , 522.  , 536.  , 493.  ,\n       487.  , 539.63, 370.  , 370.  , 390.  , 390.  , 383.  , 539.  ,\n       539.  , 554.  , 525.  , 516.  , 529.  , 541.  , 544.  , 530.  ,\n       425.  , 526.  , 522.  , 517.  , 522.5 , 420.  , 430.  , 540.  ,\n       540.  , 551.  , 550.  , 540.  , 550.  , 549.  , 335.  , 520.  ,\n       349.  , 480.  , 370.  , 440.  , 500.  , 525.  , 540.  , 351.  ,\n       501.  , 500.  , 348.  , 390.  , 360.  , 532.  , 375.  , 363.  ,\n       495.  , 440.  , 346.  , 346.  , 352.  , 440.  , 460.  , 450.  ,\n       370.  , 365.  , 460.  , 437.  , 367.  , 489.  , 520.  , 513.  ,\n       380.  , 370.  , 360.  , 361.  , 360.  , 360.  , 520.  , 355.  ,\n       490.  , 430.  , 449.  , 452.  , 432.  , 375.  , 375.  , 520.  ,\n       535.  , 361.  , 345.  , 360.  , 540.  , 460.  , 409.  , 530.  ,\n       540.  , 344.  , 350.  , 525.  , 533.  , 520.  , 530.  , 530.  ,\n       528.  , 528.  , 551.  , 540.  , 480.  , 490.  , 529.  , 518.  ,\n       490.  , 400.  , 360.  , 360.  , 480.  , 515.  , 470.  , 460.  ,\n       460.  , 490.  , 508.  , 353.  , 356.  , 365.  , 400.  , 370.  ,\n       450.  , 523.  , 538.23, 490.  , 535.  , 535.  , 508.  , 530.  ,\n       430.  , 520.  , 515.  , 510.  , 510.  , 529.  , 357.  , 520.  ,\n       530.  , 501.  , 553.  , 478.  , 560.  , 530.  , 510.  , 515.  ,\n       510.  , 570.  , 360.  , 530.  , 520.  ])", "weight": "None", "message_clsname": "'Pipeline'", "message": "None", "params": "{'fit': {}, 'partial_fit': {}, 'predict': {}, 'predict_proba': {}, 'predict_log_proba': {}, 'decision_function': {}, 'score': {}, 'split': {}, 'transform': {}, 'inverse_transform': {}, 'fit_transform': {}, 'fit_predict': {}}"}, "time": 1759843526.644744}